ansi_struct/__init__.py
ansi_struct/cli.py
ansi_struct-0.1.4.dist-info/LICENSE
ansi_struct-0.1.4.dist-info/METADATA
ansi_struct-0.1.4.dist-info/WHEEL
ansi_struct-0.1.4.dist-info/entry_points.txt
ansi_struct-0.1.4.dist-info/RECORD
